{
	"banners": [
		{
			"id": "000001",
			"src": "/static/banner/001.jpg"
		},
		{
			"id": "000002",
			"src": "/static/banner/002.jpg"
		},
		{
			"id": "000003",
			"src": "/static/banner/003.jpg"
		}
	],
	"navlist": [
		{
			"icon": "",
			"text": "特价书籍"
		},
		{
			"icon": "",
			"text": "电子书"
		},
		{
			"icon": "",
			"text": "音像管"
		},
		{
			"icon": "",
			"text": "预售订购"
		},
		{
			"icon": "",
			"text": "精品小说"
		},
		{
			"icon": "",
			"text": "必买清单"
		},
		{
			"icon": "",
			"text": "社区"
		},
		{
			"icon": "",
			"text": "会员中心"
		}
	]
}